litellm_gigachat/__init__.py
litellm_gigachat/callbacks/__init__.py
litellm_gigachat/callbacks/content_handler.py
litellm_gigachat/callbacks/internal_header_callback.py
litellm_gigachat/callbacks/token_callback.py
litellm_gigachat/cli/__init__.py
litellm_gigachat/cli/main.py
litellm_gigachat/cli/utils.py
litellm_gigachat/cli/commands/__init__.py
litellm_gigachat/cli/commands/examples.py
litellm_gigachat/cli/commands/refresh_token.py
litellm_gigachat/cli/commands/start.py
litellm_gigachat/cli/commands/test.py
litellm_gigachat/cli/commands/token_info.py
litellm_gigachat/cli/commands/version.py
litellm_gigachat/core/__init__.py
litellm_gigachat/core/gigachat_client.py
litellm_gigachat/core/internal_header_manager.py
litellm_gigachat/core/token_manager.py
litellm_gigachat/proxy/__init__.py
litellm_gigachat/proxy/server.py
litellm_gigachat-0.1.3.dist-info/licenses/LICENSE
litellm_gigachat-0.1.3.dist-info/METADATA
litellm_gigachat-0.1.3.dist-info/WHEEL
litellm_gigachat-0.1.3.dist-info/entry_points.txt
litellm_gigachat-0.1.3.dist-info/top_level.txt
litellm_gigachat-0.1.3.dist-info/RECORD
