Metadata-Version: 2.4
Name: litellm-gigachat
Version: 0.1.3
Summary: Полнофункциональная интеграция GigaChat API с LiteLLM
Author-email: LiteLLM GigaChat Team <clack008@gmail.com>
Maintainer-email: LiteLLM GigaChat Team <clack008@gmail.com>
License-Expression: MIT
Project-URL: Homepage, https://github.com/stp008/litellm-gigachat
Project-URL: Documentation, https://github.com/stp008/litellm-gigachat/blob/main/docs/README.md
Project-URL: Repository, https://github.com/stp008/litellm-gigachat.git
Project-URL: Bug Tracker, https://github.com/stp008/litellm-gigachat/issues
Keywords: gigachat,litellm,openai,api,proxy,sber,russian,llm,ai,chatbot
Classifier: Development Status :: 4 - Beta
Classifier: Intended Audience :: Developers
Classifier: Operating System :: OS Independent
Classifier: Programming Language :: Python :: 3
Classifier: Programming Language :: Python :: 3.8
Classifier: Programming Language :: Python :: 3.9
Classifier: Programming Language :: Python :: 3.10
Classifier: Programming Language :: Python :: 3.11
Classifier: Programming Language :: Python :: 3.12
Classifier: Topic :: Software Development :: Libraries :: Python Modules
Classifier: Topic :: Internet :: WWW/HTTP :: HTTP Servers
Classifier: Topic :: Scientific/Engineering :: Artificial Intelligence
Requires-Python: >=3.8
License-File: LICENSE
Requires-Dist: litellm[proxy]==1.65.1
Requires-Dist: requests<3.0.0,>=2.31.0
Requires-Dist: certifi>=2023.7.22
Requires-Dist: python-dotenv<2.0.0,>=1.0.0
Requires-Dist: click<9.0.0,>=8.0.0
Dynamic: license-file
